orchify/__init__.py
orchify/cli.py
orchify/generator.py
orchify-0.2.0.dist-info/licenses/LICENSE
orchify-0.2.0.dist-info/METADATA
orchify-0.2.0.dist-info/WHEEL
orchify-0.2.0.dist-info/entry_points.txt
orchify-0.2.0.dist-info/top_level.txt
orchify-0.2.0.dist-info/RECORD
