Metadata-Version: 2.4
Name: orchify
Version: 0.2.0
Summary: AI-driven Dockerfile generator for any Python project
Author-email: Sattyam Jain <sattyamjain96@gmail.com>
License: MIT
Project-URL: Homepage, https://github.com/sattyamjjain/Orchify
Project-URL: Repository, https://github.com/sattyamjjain/Orchify
Project-URL: Documentation, https://github.com/sattyamjjain/Orchify
Keywords: docker,dockerfile,container,containers,containerization,cli,command-line,ai,agentic-ai,aiops,devops,automation,orchestration,cicd,continuous-integration,continuous-deployment,github-actions,gitlab-ci,jenkins,infrastructure-as-code,iac,terraform,ansible,kubernetes,helm,cloud,aws,azure,gcp,serverless,pydantic,jinja2,mcp,agn0,openai,anthropic,templates,python,tooling,dev-tooling,infrastructure,monitoring,logging
Classifier: Programming Language :: Python :: 3
Classifier: Programming Language :: Python :: 3.8
Classifier: License :: OSI Approved :: MIT License
Classifier: Operating System :: OS Independent
Requires-Python: >=3.8
License-File: LICENSE
Requires-Dist: click
Requires-Dist: agno
Requires-Dist: mcp
Requires-Dist: anthropic
Requires-Dist: openai
Requires-Dist: jinja2
Dynamic: license-file
